LICENSE.md
MANIFEST.in
README.md
setup.py
django_rest_framework_signature.egg-info/PKG-INFO
django_rest_framework_signature.egg-info/SOURCES.txt
django_rest_framework_signature.egg-info/dependency_links.txt
django_rest_framework_signature.egg-info/top_level.txt
rest_framework_signature/__init__.py
rest_framework_signature/apps.py
rest_framework_signature/authentication.py
rest_framework_signature/backend.py
rest_framework_signature/errors.py
rest_framework_signature/exceptions.py
rest_framework_signature/helpers.py
rest_framework_signature/serializers.py
rest_framework_signature/settings.py
rest_framework_signature/tests.py
rest_framework_signature/urls.py
rest_framework_signature/views.py
rest_framework_signature/models/__init__.py
rest_framework_signature/models/relational.py