Metadata-Version: 2.1
Name: django-rest-framework-signature
Version: 4.0.4.dev1
Summary: Django Rest Framework Signature Authentication
Home-page: https://github.com/Skylude/django-rest-framework-signature
Author: Skyler Cain
Author-email: skylercain@gmail.com
Keywords: django rest_framework authentication api_key signature
License-File: LICENSE.md
